dent/__init__.py
dent/main.py
dent/py.typed
dent-1.0.2.data/scripts/dockerd-proxy
dent-1.0.2.dist-info/METADATA
dent-1.0.2.dist-info/WHEEL
dent-1.0.2.dist-info/entry_points.txt
dent-1.0.2.dist-info/top_level.txt
dent-1.0.2.dist-info/RECORD
