Metadata-Version: 2.4
Name: dent
Version: 1.0.2
Summary: Enter interactive shells in Docker containers and manage persistent containers
Author-email: "Curt J. Sampson" <cjs@cynic.net>, Nishant Rodrigues <nishantjr@gmail.com>
Project-URL: homepage, https://github.com/cynic-net/dent
Project-URL: source, https://github.com/cynic-net/dent
Project-URL: tracker, https://github.com/cynic-net/dent/issues
Requires-Python: >=3.8
